pykerio/__init__.py
pykerio/constants.py
pykerio/json_serializable.py
pykerio/pykerio.py
pykerio/pykerio_connect.py
pykerio/pykerio_control.py
pykerio/rpc_response.py
pykerio/enums/__init__.py
pykerio/enums/active_host_type.py
pykerio/enums/active_tool.py
pykerio/enums/activity_type.py
pykerio/enums/addressee_type.py
pykerio/enums/alert_event_rule_type.py
pykerio/enums/antivirus_status.py
pykerio/enums/antivirus_update_phases.py
pykerio/enums/api_entity.py
pykerio/enums/application_type.py
pykerio/enums/auth_method_type.py
pykerio/enums/auth_type.py
pykerio/enums/bandwidth_unit.py
pykerio/enums/base_enumeration.py
pykerio/enums/bm_condition_type.py
pykerio/enums/bm_traffic_type.py
pykerio/enums/byte_units.py
pykerio/enums/check_version_type.py
pykerio/enums/compare_operator.py
pykerio/enums/configuration_backup_phase.py
pykerio/enums/connection_direction.py
pykerio/enums/connectivity_status.py
pykerio/enums/connectivity_type.py
pykerio/enums/content_condition_entity_type.py
pykerio/enums/content_entity_url_type.py
pykerio/enums/dhcp_lease_type.py
pykerio/enums/dhcp_mode_type.py
pykerio/enums/dhcp_option_type.py
pykerio/enums/directory_service_type.py
pykerio/enums/dns_tool.py
pykerio/enums/dns_type.py
pykerio/enums/dynamic_dns_address_type.py
pykerio/enums/dynamic_dns_status.py
pykerio/enums/entity.py
pykerio/enums/expire_type.py
pykerio/enums/export_format.py
pykerio/enums/facility_unit.py
pykerio/enums/failover_role_type.py
pykerio/enums/histogram_interval_type.py
pykerio/enums/histogram_type.py
pykerio/enums/http_log_type.py
pykerio/enums/https_server_mode.py
pykerio/enums/importance.py
pykerio/enums/interface_condition_type.py
pykerio/enums/interface_encap_type.py
pykerio/enums/interface_group_type.py
pykerio/enums/interface_mode_type.py
pykerio/enums/interface_status_type.py
pykerio/enums/interface_type.py
pykerio/enums/intrusion_prevention_action.py
pykerio/enums/intrusion_prevention_update_phases.py
pykerio/enums/ip_version.py
pykerio/enums/item_name.py
PyKerio-0.5.0.dist-info/LICENSE
PyKerio-0.5.0.dist-info/METADATA
PyKerio-0.5.0.dist-info/WHEEL
PyKerio-0.5.0.dist-info/top_level.txt
PyKerio-0.5.0.dist-info/RECORD
